dbini/__init__.py
dbini/core.py
dbini/server.py
dbini-1.0.1.dist-info/licenses/LICENSE
dbini-1.0.1.dist-info/METADATA
dbini-1.0.1.dist-info/WHEEL
dbini-1.0.1.dist-info/top_level.txt
dbini-1.0.1.dist-info/RECORD
