Metadata-Version: 2.4
Name: dbini
Version: 1.0.1
Summary: Zero-config NoSQL backend database as a Python package
Author-email: Binidu Ranasinghe <rbinidu@gmail.com>
License: MIT
Project-URL: Homepage, https://github.com/Binidu01/dbini
Keywords: NoSQL,database,JSON,Python,local-first,file-based DB,FastAPI,REST API,WebSocket
Requires-Python: >=3.9
License-File: LICENSE
Requires-Dist: fastapi
Requires-Dist: uvicorn
Dynamic: license-file
